odoo/addons/product_contract_brand/README.rst
odoo/addons/product_contract_brand/__init__.py
odoo/addons/product_contract_brand/__manifest__.py
odoo/addons/product_contract_brand/i18n/it.po
odoo/addons/product_contract_brand/i18n/product_contract_brand.pot
odoo/addons/product_contract_brand/models/__init__.py
odoo/addons/product_contract_brand/models/sale_order.py
odoo/addons/product_contract_brand/readme/CONTRIBUTORS.md
odoo/addons/product_contract_brand/readme/DESCRIPTION.md
odoo/addons/product_contract_brand/static/description/icon.png
odoo/addons/product_contract_brand/static/description/index.html
odoo/addons/product_contract_brand/tests/__init__.py
odoo/addons/product_contract_brand/tests/test_sale_order.py
odoo_addon_product_contract_brand-18.0.1.0.0.4.dist-info/METADATA
odoo_addon_product_contract_brand-18.0.1.0.0.4.dist-info/WHEEL
odoo_addon_product_contract_brand-18.0.1.0.0.4.dist-info/top_level.txt
odoo_addon_product_contract_brand-18.0.1.0.0.4.dist-info/RECORD
