Metadata-Version: 2.1
Name: odoo-addon-product_contract_brand
Version: 18.0.1.0.0.4
Requires-Python: >=3.10
Requires-Dist: odoo-addon-contract_brand==18.0.*
Requires-Dist: odoo-addon-product_contract==18.0.*
Requires-Dist: odoo-addon-sale_brand==18.0.*
Requires-Dist: odoo==18.0.*
Summary: This addon propagate the brand from sale order to contract
Home-page: https://github.com/OCA/brand
License: AGPL-3
Author: ACSONE SA/NV,Odoo Community Association (OCA)
Author-email: support@odoo-community.org
Classifier: Programming Language :: Python
Classifier: Framework :: Odoo
Classifier: Framework :: Odoo :: 18.0
Classifier: License :: OSI Approved :: GNU Affero General Public License v3
